multiplayer/py.typed
multiplayer/opentelemetry/constants/__init__.py
multiplayer/opentelemetry/exporter/grpc/log_exporter/__init__.py
multiplayer/opentelemetry/exporter/grpc/trace_exporter/__init__.py
multiplayer/opentelemetry/exporter/http/log_exporter/__init__.py
multiplayer/opentelemetry/exporter/http/trace_exporter/__init__.py
multiplayer/opentelemetry/trace/id_generator.py
multiplayer/opentelemetry/trace/sampler.py
multiplayer/opentelemetry/version/__init__.py
multiplayer_opentelemetry-0.0.8.dist-info/METADATA
multiplayer_opentelemetry-0.0.8.dist-info/WHEEL
multiplayer_opentelemetry-0.0.8.dist-info/entry_points.txt
multiplayer_opentelemetry-0.0.8.dist-info/licenses/LICENSE
multiplayer_opentelemetry-0.0.8.dist-info/RECORD
