Metadata-Version: 2.4
Name: multiplayer-opentelemetry
Version: 0.0.8
Summary: Multiplayer OpenTelemetry Python API
Project-URL: Homepage, https://github.com/multiplayer-app/multiplayer-otlp-python
Project-URL: Repository, https://github.com/multiplayer-app/multiplayer-otlp-python
Author-email: Multiplayer Authors <hello@multiplayer.app>
License: Apache-2.0
License-File: LICENSE
Classifier: Development Status :: 5 - Production/Stable
Classifier: Framework :: OpenTelemetry
Classifier: Intended Audience :: Developers
Classifier: License :: OSI Approved :: Apache Software License
Classifier: Programming Language :: Python
Classifier: Programming Language :: Python :: 3
Classifier: Programming Language :: Python :: 3.8
Classifier: Programming Language :: Python :: 3.9
Classifier: Programming Language :: Python :: 3.10
Classifier: Programming Language :: Python :: 3.11
Classifier: Programming Language :: Python :: 3.12
Classifier: Programming Language :: Python :: 3.13
Classifier: Typing :: Typed
Requires-Python: >=3.8
Requires-Dist: opentelemetry-api>=1.29.0
Requires-Dist: opentelemetry-exporter-otlp-proto-grpc>=1.29.0
Requires-Dist: opentelemetry-exporter-otlp-proto-http>=1.29.0
Requires-Dist: opentelemetry-sdk>=1.29.0
